README.md
setup.cfg
setup.py
nasbench_keras/__init__.py
nasbench_keras/base_ops.py
nasbench_keras/generate_graphs.py
nasbench_keras/graph_util.py
nasbench_keras/model_spec.py
nasbench_keras/nasbench_keras.py
nasbench_keras.egg-info/PKG-INFO
nasbench_keras.egg-info/SOURCES.txt
nasbench_keras.egg-info/dependency_links.txt
nasbench_keras.egg-info/requires.txt
nasbench_keras.egg-info/top_level.txt