Metadata-Version: 1.1
Name: nasbench-keras
Version: 0.2
Summary: NAS-Bench 101 to Tensorflow 2.0 (tf.keras) converter
Home-page: https://github.com/evgps/nasbench_keras
Author: evgps
Author-email: evgps@ya.ru
License: MIT License
Download-URL: https://github.com/evgps/nasbench_keras/archive/v_01.tar.gz
Keywords: NAS,Converter,Tensorflow,Keras
Platform: UNKNOWN
Classifier: Development Status :: 3 - Alpha
Classifier: Intended Audience :: Developers
Classifier: Topic :: Software Development :: Build Tools
Classifier: License :: OSI Approved :: MIT License
Classifier: Programming Language :: Python :: 3
